pyCAIR/__init__.py
pyCAIR/helpers.py
pyCAIR/imgtovideos.py
pyCAIR/notdoneyet.py
pyCAIR/opencv_generators.py
pyCAIR/seam_carve.py
pyCAIR-0.1.13.dist-info/METADATA
pyCAIR-0.1.13.dist-info/RECORD
pyCAIR-0.1.13.dist-info/WHEEL
pyCAIR-0.1.13.dist-info/top_level.txt
