Metadata-Version: 2.1
Name: pyCAIR
Version: 0.1.13
Summary: This module provides a simple yet powerful mechanism to resize images using Seam Carving Algorithm.
Home-page: https://github.com/avidLearnerInProgress/pyCAIR
Author: Chirag Shah
Author-email: chiragshah9696@gmail.com
License: GPL-3.0
Download-URL: https://github.com/avidLearnerInProgress/pyCAIR/archive/0.1.tar.gz
Keywords: python,openCV,image-processing,dynamic-programming,seam-carving
Platform: UNKNOWN
